bdist_pyinstaller/__init__.py
bdist_pyinstaller/bdist_pyinstaller.py
bdist_pyinstaller-0.2.1.dist-info/LICENSE
bdist_pyinstaller-0.2.1.dist-info/METADATA
bdist_pyinstaller-0.2.1.dist-info/WHEEL
bdist_pyinstaller-0.2.1.dist-info/entry_points.txt
bdist_pyinstaller-0.2.1.dist-info/top_level.txt
bdist_pyinstaller-0.2.1.dist-info/RECORD
