Metadata-Version: 2.1
Name: bdist-pyinstaller
Version: 0.2.1
Summary: A side-car distutils command to automate creation of the pyinstaller packages in a non-intrusive way
Home-page: https://github.com/AmadeusITGroup/bdist_pyinstaller
Author: Waldek Herka
Author-email: wherka-ama@users.noreply.github.com
Maintainer: Waldek Herka
Maintainer-email: wherka-ama@users.noreply.github.com
License: Apache-2.0
Project-URL: Issue Tracker, https://github.com/AmadeusITGroup/bdist_pyinstaller/issues
Keywords: PyInstaller,packaging
Platform: UNKNOWN
Classifier: Development Status :: 2 - Pre-Alpha
Classifier: Intended Audience :: Developers
Classifier: Topic :: System :: Archiving :: Packaging
Classifier: License :: OSI Approved :: Apache Software License
Classifier: Programming Language :: Python
Classifier: Programming Language :: Python :: 3
Classifier: Programming Language :: Python :: 3.5
Classifier: Programming Language :: Python :: 3.6
Classifier: Programming Language :: Python :: 3.7
Classifier: Programming Language :: Python :: 3.8
Classifier: Programming Language :: Python :: 3.9
Requires-Python: !=3.0.*,!=3.1.*,!=3.2.*,!=3.3.*,!=3.4.*,>=2.7
License-File: LICENSE
Provides-Extra: test
Requires-Dist: pytest (>=3.0.0) ; extra == 'test'
Requires-Dist: pytest-cov ; extra == 'test'
